Workbook

Sheet 1_MASTER_RATES
A1: 1. PRODUCT MASTER & WORK CENTER RATES (SYNTHETIC MOCK)
A3: SECTION A: PRODUCT MASTER
A4: Product Code | B4: Product Description | C4: UOM | D4: Customer / Application | E4: Effective Date
A5: MOCK-DEMO-001 | B5: SYNTHETIC SAMPLE ASSEMBLY (DEMO & TEST SUITE) | C5: PC | D5: BENCHMARK TEST | E5: 2026-01-01
A7: SECTION B: WORK CENTER RATES (4 DEPARTMENTS)
A8: Department (WC Name) | B8: Line / Department Description | C8: Labor Rate (THB/MHr) | D8: Burden Rate (THB/MHr) | E8: Source Reference
A9: WC-FABRICATION | B9: Raw Material Prep & Stamping | C9: 110 | D9: 140 | E9: Ref-Std-Rate-2026
A10: WC-PRINTING | B10: Precision Cleanroom Screen Printing | C10: 105 | D10: 100 | E10: Ref-Std-Rate-2026
A11: WC-ASSEMBLY | B11: Automated SMT & Module Assembly | C11: 105 | D11: 90 | E11: Ref-Std-Rate-2026
A12: WC-QA-PACK | B12: Final Automated QA Inspection & Packaging | C12: 100 | D12: 80 | E12: Ref-Std-Rate-2026

Sheet 2_BOM_BREAKDOWN
A1: 2. DIRECT MATERIAL BREAKDOWN (BOM)
A3: TABLE 1: BOM INPUT PARAMETERS (10 ITEMS)
A4: No | B4: Item Code | C4: Material Description | D4: Usage (Q) | E4: Unit | F4: Base Price P0 | G4: Active Price P1 | H4: Base Loss L0 | I4: Active Loss L1 | J4: Source Reference
A5: 1 | B5: MAT-FILM-01 | C5: PET Optical Substrate Film (0.5m x 500m) | D5: 0.025 | E5: SM | F5: 50 | G5: 50 | H5: 0.15 | I5: 0.25 | J5: Loss Spike (+10%)
A6: 2 | B6: MAT-PASTE-02 | C6: Conductive Silver Paste Type-A | D6: 0.2 | E6: GM | F6: 30 | G6: 55 | H6: 0.2 | I6: 0.2 | J6: Commodity Inflation (+25 THB/g)
A7: 3 | B7: MAT-INK-03 | C7: Dielectric Carbon Conductive Ink | D7: 0.08 | E7: GM | F7: 15 | G7: 12 | H7: 0.1 | I7: 0.1 | J7: Vendor Discount (-3 THB/g)
A8: 4 | B8: MAT-TAPE-04 | C8: Double-Sided Acrylic Spacer Tape | D8: 0.015 | E8: SM | F8: 80 | G8: 80 | H8: 0.1 | I8: 0.1 | J8: Standard Contract
A9: 5 | B9: MAT-LABEL-05 | C9: QR Code Serialized Polyimide Label | D9: 1 | E9: PC | F9: 0.15 | G9: 0.25 | H9: 0.05 | I9: 0.05 | J9: Minor Price Increase
A10: 6 | B10: MAT-SOLVENT-06 | C10: Industrial Degreaser & Thinner | D10: 0.05 | E10: GM | F10: 2 | G10: 2 | H10: 0.1 | I10: 0.1 | J10: Standard Chemical
A11: 7 | B11: MAT-CONN-07 | C11: FPC Flexible Tail Header Connector | D11: 1 | E11: PC | F11: 5 | G11: 5.8 | H11: 0.02 | I11: 0.02 | J11: Supplier Price Update
A12: 8 | B12: MAT-RESIN-08 | C12: UV Curable Hardcoat Protection Resin | D12: 0.1 | E12: GM | F12: 8 | G12: 8 | H12: 0.15 | I12: 0.15 | J12: Standard Chemical
A13: 9 | B13: MAT-LINER-09 | C13: PE Protective Masking Film Liner | D13: 0.03 | E13: SM | F13: 12 | G13: 12 | H13: 0.1 | I13: 0.18 | J13: Handling Scrap
A14: 10 | B14: MAT-PACK-10 | C14: Anti-Static Tray & Outer Shipping Carton | D14: 0.05 | E14: SET | F14: 20 | G14: 20 | H14: 0 | I14: 0 | J14: Standard Packaging
A16: TABLE 2: BOM CALCULATION ENGINE & LEVEL 3 VARIANCE
A17: No | B17: Item Code | C17: Material Description | D17: Base Cost P0 | E17: Active Cost P1 | F17: Total Variance | G17: Price Var (MPV) | H17: Loss Var (MLV) | I17: % Contrib | J17: Traceability
A18: =A5 | B18: =B5 | C18: =C5 | D18: =D5*F5*(1+H5) | E18: =D5*G5*(1+I5) | F18: =E18-D18 | G18: =(G5-F5)*D5*(1+I5) | H18: =(I5-H5)*D5*F5 | I18: =IF(F$28<>0, F18/F$28, 0) | J18: =J5
A19: =A6 | B19: =B6 | C19: =C6 | D19: =D6*F6*(1+H6) | E19: =D6*G6*(1+I6) | F19: =E19-D19 | G19: =(G6-F6)*D6*(1+I6) | H19: =(I6-H6)*D6*F6 | I19: =IF(F$28<>0, F19/F$28, 0) | J19: =J6
A20: =A7 | B20: =B7 | C20: =C7 | D20: =D7*F7*(1+H7) | E20: =D7*G7*(1+I7) | F20: =E20-D20 | G20: =(G7-F7)*D7*(1+I7) | H20: =(I7-H7)*D7*F7 | I20: =IF(F$28<>0, F20/F$28, 0) | J20: =J7
A21: =A8 | B21: =B8 | C21: =C8 | D21: =D8*F8*(1+H8) | E21: =D8*G8*(1+I8) | F21: =E21-D21 | G21: =(G8-F8)*D8*(1+I8) | H21: =(I8-H8)*D8*F8 | I21: =IF(F$28<>0, F21/F$28, 0) | J21: =J8
A22: =A9 | B22: =B9 | C22: =C9 | D22: =D9*F9*(1+H9) | E22: =D9*G9*(1+I9) | F22: =E22-D22 | G22: =(G9-F9)*D9*(1+I9) | H22: =(I9-H9)*D9*F9 | I22: =IF(F$28<>0, F22/F$28, 0) | J22: =J9
A23: =A10 | B23: =B10 | C23: =C10 | D23: =D10*F10*(1+H10) | E23: =D10*G10*(1+I10) | F23: =E23-D23 | G23: =(G10-F10)*D10*(1+I10) | H23: =(I10-H10)*D10*F10 | I23: =IF(F$28<>0, F23/F$28, 0) | J23: =J10
A24: =A11 | B24: =B11 | C24: =C11 | D24: =D11*F11*(1+H11) | E24: =D11*G11*(1+I11) | F24: =E24-D24 | G24: =(G11-F11)*D11*(1+I11) | H24: =(I11-H11)*D11*F11 | I24: =IF(F$28<>0, F24/F$28, 0) | J24: =J11
A25: =A12 | B25: =B12 | C25: =C12 | D25: =D12*F12*(1+H12) | E25: =D12*G12*(1+I12) | F25: =E25-D25 | G25: =(G12-F12)*D12*(1+I12) | H25: =(I12-H12)*D12*F12 | I25: =IF(F$28<>0, F25/F$28, 0) | J25: =J12
A26: =A13 | B26: =B13 | C26: =C13 | D26: =D13*F13*(1+H13) | E26: =D13*G13*(1+I13) | F26: =E26-D26 | G26: =(G13-F13)*D13*(1+I13) | H26: =(I13-H13)*D13*F13 | I26: =IF(F$28<>0, F26/F$28, 0) | J26: =J13
A27: =A14 | B27: =B14 | C27: =C14 | D27: =D14*F14*(1+H14) | E27: =D14*G14*(1+I14) | F27: =E27-D27 | G27: =(G14-F14)*D14*(1+I14) | H27: =(I14-H14)*D14*F14 | I27: =IF(F$28<>0, F27/F$28, 0) | J27: =J14
C28: TOTAL DIRECT MATERIAL COST (C_M) | D28: =SUM(D18:D27) | E28: =SUM(E18:E27) | F28: =SUM(F18:F27) | G28: =SUM(G18:G27) | H28: =SUM(H18:H27)

Sheet 3_ROUTING_BREAKDOWN
A1: 3. CONVERSION PROCESS ROUTING BREAKDOWN
A3: TABLE 1: ROUTING PROCESS INPUT (15 STEPS)
A4: Op Seq | B4: Operation Description | C4: Department (WC) | D4: Manning | E4: Base Cap (pc/hr) | F4: Active Cap (pc/hr) | G4: Base Yield | H4: Active Yield | I4: Source Reference
A5: 10 | B5: Raw Sheet Precision Cutting | C5: WC-FABRICATION | D5: 1 | E5: 5000 | F5: 5000 | G5: 1 | H5: 1 | I5: Standard Process
A6: 20 | B6: Thermal Pre-Shrink Annealing | C6: WC-FABRICATION | D6: 1 | E6: 2000 | F6: 2000 | G6: 1 | H6: 1 | I6: Standard Process
A7: 30 | B7: Cleanroom Sheet Dust Removal | C7: WC-PRINTING | D7: 0.5 | E7: 6000 | F7: 6000 | G7: 1 | H7: 1 | I7: Standard Process
A8: 40 | B8: Silver Conductor Circuit Printing | C8: WC-PRINTING | D8: 2 | E8: 1500 | F8: 1000 | G8: 1 | H8: 1 | I8: Machine Speed Drop (-33%)
A9: 50 | B9: IR Oven Tunnel Curing #1 | C9: WC-PRINTING | D9: 1 | E9: 3000 | F9: 3000 | G9: 1 | H9: 1 | I9: Standard Process
A10: 60 | B10: Carbon Resistor Jumper Printing | C10: WC-PRINTING | D10: 2 | E10: 1800 | F10: 1800 | G10: 0.98 | H10: 0.98 | I10: Standard Process
A11: 70 | B11: Dielectric Insulation Overcoat | C11: WC-PRINTING | D11: 2 | E11: 1600 | F11: 1600 | G11: 0.98 | H11: 0.98 | I11: Standard Process
A12: 80 | B12: Multi-Layer Membrane Lamination | C12: WC-ASSEMBLY | D12: 2 | E12: 2000 | F12: 2000 | G12: 0.99 | H12: 0.99 | I12: Standard Process
A13: 90 | B13: High-Speed Perimeter Die Punching | C13: WC-ASSEMBLY | D13: 1 | E13: 4000 | F13: 4000 | G13: 0.98 | H13: 0.98 | I13: Standard Process
A14: 100 | B14: Auto Optical Defect Inspection (AOI) | C14: WC-ASSEMBLY | D14: 2 | E14: 800 | F14: 800 | G14: 0.9 | H14: 0.7 | I14: Severe Yield Drop (90% -> 70%)
A15: 110 | B15: SMT Component Pick & Place | C15: WC-ASSEMBLY | D15: 1 | E15: 1200 | F15: 900 | G15: 0.95 | H15: 0.95 | I15: Feeder Jam Bottleneck
A16: 120 | B16: Hot-Bar Soldering & UV Curing | C16: WC-ASSEMBLY | D16: 2 | E16: 1000 | F16: 1000 | G16: 0.96 | H16: 0.96 | I16: Standard Process
... A19: 150 | B19: Final Barcode Scan & Master Packaging | C19: WC-QA-PACK | D19: 2 | E19: 600 | F19: 600 | G19: 1 | H19: 1 | I19: Standard Process
A21: TABLE 2: CONVERSION COST ENGINE (LABOR & BURDEN PER UNIT)
A22: Op Seq | B22: Operation Description | C22: Department | D22: Base Labor | E22: Active Labor | F22: Base Burden | G22: Active Burden | H22: Total Conv Base | I22: Total Conv Active | J22: Net Variance
A23: =A5 | B23: =B5 | C23: =C5 | D23: =(D5/(E5*G5))*VLOOKUP(C5,'1_MASTER_RATES'!$A$9:$D$12,3,FALSE) | E23: =(D5/(F5*H5))*VLOOKUP(C5,'1_MASTER_RATES'!$A$9:$D$12,3,FALSE) | F23: =(D5/(E5*G5))*VLOOKUP(C5,'1_MASTER_RATES'!$A$9:$D$12,4,FALSE) | G23: =(D5/(F5*H5))*VLOOKUP(C5,'1_MASTER_RATES'!$A$9:$D$12,4,FALSE) | H23: =D23+F23 | I23: =E23+G23 | J23: =I23-H23
A24: =A6 | B24: =B6 | C24: =C6 | D24: =(D6/(E6*G6))*VLOOKUP(C6,'1_MASTER_RATES'!$A$9:$D$12,3,FALSE) | E24: =(D6/(F6*H6))*VLOOKUP(C6,'1_MASTER_RATES'!$A$9:$D$12,3,FALSE) | F24: =(D6/(E6*G6))*VLOOKUP(C6,'1_MASTER_RATES'!$A$9:$D$12,4,FALSE) | G24: =(D6/(F6*H6))*VLOOKUP(C6,'1_MASTER_RATES'!$A$9:$D$12,4,FALSE) | H24: =D24+F24 | I24: =E24+G24 | J24: =I24-H24
A25: =A7 | B25: =B7 | C25: =C7 | D25: =(D7/(E7*G7))*VLOOKUP(C7,'1_MASTER_RATES'!$A$9:$D$12,3,FALSE) | E25: =(D7/(F7*H7))*VLOOKUP(C7,'1_MASTER_RATES'!$A$9:$D$12,3,FALSE) | F25: =(D7/(E7*G7))*VLOOKUP(C7,'1_MASTER_RATES'!$A$9:$D$12,4,FALSE) | G25: =(D7/(F7*H7))*VLOOKUP(C7,'1_MASTER_RATES'!$A$9:$D$12,4,FALSE) | H25: =D25+F25 | I25: =E25+G25 | J25: =I25-H25
A26: =A8 | B26: =B8 | C26: =C8 | D26: =(D8/(E8*G8))*VLOOKUP(C8,'1_MASTER_RATES'!$A$9:$D$12,3,FALSE) | E26: =(D8/(F8*H8))*VLOOKUP(C8,'1_MASTER_RATES'!$A$9:$D$12,3,FALSE) | F26: =(D8/(E8*G8))*VLOOKUP(C8,'1_MASTER_RATES'!$A$9:$D$12,4,FALSE) | G26: =(D8/(F8*H8))*VLOOKUP(C8,'1_MASTER_RATES'!$A$9:$D$12,4,FALSE) | H26: =D26+F26 | I26: =E26+G26 | J26: =I26-H26
A27: =A9 | B27: =B9 | C27: =C9 | D27: =(D9/(E9*G9))*VLOOKUP(C9,'1_MASTER_RATES'!$A$9:$D$12,3,FALSE) | E27: =(D9/(F9*H9))*VLOOKUP(C9,'1_MASTER_RATES'!$A$9:$D$12,3,FALSE) | F27: =(D9/(E9*G9))*VLOOKUP(C9,'1_MASTER_RATES'!$A$9:$D$12,4,FALSE) | G27: =(D9/(F9*H9))*VLOOKUP(C9,'1_MASTER_RATES'!$A$9:$D$12,4,FALSE) | H27: =D27+F27 | I27: =E27+G27 | J27: =I27-H27
A28: =A10 | B28: =B10 | C28: =C10 | D28: =(D10/(E10*G10))*VLOOKUP(C10,'1_MASTER_RATES'!$A$9:$D$12,3,FALSE) | E28: =(D10/(F10*H10))*VLOOKUP(C10,'1_MASTER_RATES'!$A$9:$D$12,3,FALSE) | F28: =(D10/(E10*G10))*VLOOKUP(C10,'1_MASTER_RATES'!$A$9:$D$12,4,FALSE) | G28: =(D10/(F10*H10))*VLOOKUP(C10,'1_MASTER_RATES'!$A$9:$D$12,4,FALSE) | H28: =D28+F28 | I28: =E28+G28 | J28: =I28-H28
A29: =A11 | B29: =B11 | C29: =C11 | D29: =(D11/(E11*G11))*VLOOKUP(C11,'1_MASTER_RATES'!$A$9:$D$12,3,FALSE) | E29: =(D11/(F11*H11))*VLOOKUP(C11,'1_MASTER_RATES'!$A$9:$D$12,3,FALSE) | F29: =(D11/(E11*G11))*VLOOKUP(C11,'1_MASTER_RATES'!$A$9:$D$12,4,FALSE) | G29: =(D11/(F11*H11))*VLOOKUP(C11,'1_MASTER_RATES'!$A$9:$D$12,4,FALSE) | H29: =D29+F29 | I29: =E29+G29 | J29: =I29-H29
A30: =A12 | B30: =B12 | C30: =C12 | D30: =(D12/(E12*G12))*VLOOKUP(C12,'1_MASTER_RATES'!$A$9:$D$12,3,FALSE) | E30: =(D12/(F12*H12))*VLOOKUP(C12,'1_MASTER_RATES'!$A$9:$D$12,3,FALSE) | F30: =(D12/(E12*G12))*VLOOKUP(C12,'1_MASTER_RATES'!$A$9:$D$12,4,FALSE) | G30: =(D12/(F12*H12))*VLOOKUP(C12,'1_MASTER_RATES'!$A$9:$D$12,4,FALSE) | H30: =D30+F30 | I30: =E30+G30 | J30: =I30-H30
A31: =A13 | B31: =B13 | C31: =C13 | D31: =(D13/(E13*G13))*VLOOKUP(C13,'1_MASTER_RATES'!$A$9:$D$12,3,FALSE) | E31: =(D13/(F13*H13))*VLOOKUP(C13,'1_MASTER_RATES'!$A$9:$D$12,3,FALSE) | F31: =(D13/(E13*G13))*VLOOKUP(C13,'1_MASTER_RATES'!$A$9:$D$12,4,FALSE) | G31: =(D13/(F13*H13))*VLOOKUP(C13,'1_MASTER_RATES'!$A$9:$D$12,4,FALSE) | H31: =D31+F31 | I31: =E31+G31 | J31: =I31-H31
A32: =A14 | B32: =B14 | C32: =C14 | D32: =(D14/(E14*G14))*VLOOKUP(C14,'1_MASTER_RATES'!$A$9:$D$12,3,FALSE) | E32: =(D14/(F14*H14))*VLOOKUP(C14,'1_MASTER_RATES'!$A$9:$D$12,3,FALSE) | F32: =(D14/(E14*G14))*VLOOKUP(C14,'1_MASTER_RATES'!$A$9:$D$12,4,FALSE) | G32: =(D14/(F14*H14))*VLOOKUP(C14,'1_MASTER_RATES'!$A$9:$D$12,4,FALSE) | H32: =D32+F32 | I32: =E32+G32 | J32: =I32-H32
A33: =A15 | B33: =B15 | C33: =C15 | D33: =(D15/(E15*G15))*VLOOKUP(C15,'1_MASTER_RATES'!$A$9:$D$12,3,FALSE) | E33: =(D15/(F15*H15))*VLOOKUP(C15,'1_MASTER_RATES'!$A$9:$D$12,3,FALSE) | F33: =(D15/(E15*G15))*VLOOKUP(C15,'1_MASTER_RATES'!$A$9:$D$12,4,FALSE) | G33: =(D15/(F15*H15))*VLOOKUP(C15,'1_MASTER_RATES'!$A$9:$D$12,4,FALSE) | H33: =D33+F33 | I33: =E33+G33 | J33: =I33-H33
A34: =A16 | B34: =B16 | C34: =C16 | D34: =(D16/(E16*G16))*VLOOKUP(C16,'1_MASTER_RATES'!$A$9:$D$12,3,FALSE) | E34: =(D16/(F16*H16))*VLOOKUP(C16,'1_MASTER_RATES'!$A$9:$D$12,3,FALSE) | F34: =(D16/(E16*G16))*VLOOKUP(C16,'1_MASTER_RATES'!$A$9:$D$12,4,FALSE) | G34: =(D16/(F16*H16))*VLOOKUP(C16,'1_MASTER_RATES'!$A$9:$D$12,4,FALSE) | H34: =D34+F34 | I34: =E34+G34 | J34: =I34-H34
... A37: =A19 | B37: =B19 | C37: =C19 | D37: =(D19/(E19*G19))*VLOOKUP(C19,'1_MASTER_RATES'!$A$9:$D$12,3,FALSE) | E37: =(D19/(F19*H19))*VLOOKUP(C19,'1_MASTER_RATES'!$A$9:$D$12,3,FALSE) | F37: =(D19/(E19*G19))*VLOOKUP(C19,'1_MASTER_RATES'!$A$9:$D$12,4,FALSE) | G37: =(D19/(F19*H19))*VLOOKUP(C19,'1_MASTER_RATES'!$A$9:$D$12,4,FALSE) | H37: =D37+F37 | I37: =E37+G37 | J37: =I37-H37
B38: TOTAL CONVERSION COST (C_L + C_B) | D38: =SUM(D23:D37) | E38: =SUM(E23:E37) | F38: =SUM(F23:F37) | G38: =SUM(G23:G37) | H38: =SUM(H23:H37) | I38: =SUM(I23:I37) | J38: =SUM(J23:J37)

Sheet 4_SUMMARY_&_COMPARISON
A1: 4. EXECUTIVE COST SUMMARY & TOP 10 DRIVERS
A4: Cost Element | B4: Baseline Std Cost | C4: Active Std Cost | D4: Net Variance | E4: % Change
A5: Direct Material (C_M) | B5: ='2_BOM_BREAKDOWN'!D28 | C5: ='2_BOM_BREAKDOWN'!E28 | D5: =C5-B5 | E5: =IF(B5<>0, D5/B5, 0)
A6: Direct Labor (C_L) | B6: ='3_ROUTING_BREAKDOWN'!D38 | C6: ='3_ROUTING_BREAKDOWN'!E38 | D6: =C6-B6 | E6: =IF(B6<>0, D6/B6, 0)
A7: Manufacturing Burden (C_B) | B7: ='3_ROUTING_BREAKDOWN'!F38 | C7: ='3_ROUTING_BREAKDOWN'!G38 | D7: =C7-B7 | E7: =IF(B7<>0, D7/B7, 0)
A8: TOTAL STANDARD COST | B8: =SUM(B5:B7) | C8: =SUM(C5:C7) | D8: =C8-B8 | E8: =IF(B8<>0, D8/B8, 0)
